dj_rest_auth_mfa/__init__.py
dj_rest_auth_mfa/adapters.py
dj_rest_auth_mfa/admin.py
dj_rest_auth_mfa/apps.py
dj_rest_auth_mfa/serializers.py
dj_rest_auth_mfa/urls.py
dj_rest_auth_mfa/utils.py
dj_rest_auth_mfa/views.py
dj_rest_auth_mfa/migrations/__init__.py
dj_rest_auth_mfa/recovery/__init__.py
dj_rest_auth_mfa/recovery/adapters.py
dj_rest_auth_mfa/recovery/serializers.py
dj_rest_auth_mfa/recovery/urls.py
dj_rest_auth_mfa/recovery/views.py
dj_rest_auth_mfa/totp/__init__.py
dj_rest_auth_mfa/totp/adapters.py
dj_rest_auth_mfa/totp/serializers.py
dj_rest_auth_mfa/totp/urls.py
dj_rest_auth_mfa/totp/views.py
dj_rest_auth_mfa-0.0.2.dist-info/LICENSE
dj_rest_auth_mfa-0.0.2.dist-info/METADATA
dj_rest_auth_mfa-0.0.2.dist-info/WHEEL
dj_rest_auth_mfa-0.0.2.dist-info/top_level.txt
dj_rest_auth_mfa-0.0.2.dist-info/RECORD
