Metadata-Version: 2.1
Name: dj-rest-auth-mfa
Version: 0.0.2
Summary: A Django App that adds MFA endpoints to dj-rest-auth
Home-page: https://github.com/oussjarrousse/dj-rest-auth-saml
Author: Oussama Jarrousse
Author-email: oussama@jarrousse.org
License: MIT
Project-URL: Source, https://github.com/oussjarrousse/dj-rest-auth-mfa/
Project-URL: Tracker, https://github.com/oussjarrousse/dj-rest-auth-mfa/issues
Keywords: Django REST allauth dj-rest-auth mfa totp 2fa authentication otp
Platform: any
Classifier: Framework :: Pytest
Classifier: Programming Language :: Python :: 3
Classifier: License :: OSI Approved :: MIT License
Classifier: Operating System :: OS Independent
Classifier: Intended Audience :: Developers
Classifier: Programming Language :: Python :: 3.8
Classifier: Programming Language :: Python :: 3.9
Classifier: Programming Language :: Python :: 3.10
Classifier: Programming Language :: Python :: 3.11
Classifier: Programming Language :: Python :: 3.12
Classifier: Programming Language :: Python :: 3 :: Only
Classifier: Topic :: Software Development :: Testing
Requires-Python: >=3.6
License-File: LICENSE
Requires-Dist: Django >=4.1.7
Requires-Dist: djangorestframework >=3.14.0
Requires-Dist: djangorestframework-simplejwt
Requires-Dist: django-cors-headers
Requires-Dist: dj-rest-auth
Requires-Dist: django-allauth ==0.57.0
Requires-Dist: django-mfa2
Provides-Extra: dev
Requires-Dist: pre-commit ; extra == 'dev'
Requires-Dist: tox ; extra == 'dev'
